argilla_sdk-0.1.0a3.dist-info/METADATA
argilla_sdk-0.1.0a3.dist-info/WHEEL
argilla_sdk-0.1.0a3.dist-info/licenses/LICENSE
argilla_sdk-0.1.0a3.dist-info/licenses/LICENSE_HEADER
argilla_sdk/__init__.py
argilla_sdk/_api/__init__.py
argilla_sdk/_api/_base.py
argilla_sdk/_api/_client.py
argilla_sdk/_api/_datasets.py
argilla_sdk/_api/_fields.py
argilla_sdk/_api/_http/__init__.py
argilla_sdk/_api/_http/_client.py
argilla_sdk/_api/_http/_helpers.py
argilla_sdk/_api/_metadata.py
argilla_sdk/_api/_questions.py
argilla_sdk/_api/_records.py
argilla_sdk/_api/_users.py
argilla_sdk/_api/_vectors.py
argilla_sdk/_api/_workspaces.py
argilla_sdk/_constants.py
argilla_sdk/_exceptions/__init__.py
argilla_sdk/_exceptions/_api.py
argilla_sdk/_exceptions/_base.py
argilla_sdk/_exceptions/_metadata.py
argilla_sdk/_exceptions/_serialization.py
argilla_sdk/_exceptions/_settings.py
argilla_sdk/_helpers/__init__.py
argilla_sdk/_helpers/_dataclasses.py
argilla_sdk/_helpers/_iterator.py
argilla_sdk/_helpers/_log.py
argilla_sdk/_helpers/_mixins.py
argilla_sdk/_helpers/_resource_repr.py
argilla_sdk/_models/__init__.py
argilla_sdk/_models/_base.py
argilla_sdk/_models/_dataset.py
argilla_sdk/_models/_record/__init__.py
argilla_sdk/_models/_record/_metadata.py
argilla_sdk/_models/_record/_record.py
argilla_sdk/_models/_record/_response.py
argilla_sdk/_models/_record/_suggestion.py
argilla_sdk/_models/_record/_vector.py
argilla_sdk/_models/_resource.py
argilla_sdk/_models/_search.py
argilla_sdk/_models/_settings/__init__.py
argilla_sdk/_models/_settings/_fields.py
argilla_sdk/_models/_settings/_metadata.py
argilla_sdk/_models/_settings/_questions/__init__.py
argilla_sdk/_models/_settings/_questions/_base.py
argilla_sdk/_models/_settings/_questions/_label_selection.py
argilla_sdk/_models/_settings/_questions/_multi_label_selection.py
argilla_sdk/_models/_settings/_questions/_ranking.py
argilla_sdk/_models/_settings/_questions/_rating.py
argilla_sdk/_models/_settings/_questions/_span.py
argilla_sdk/_models/_settings/_questions/_text.py
argilla_sdk/_models/_user.py
argilla_sdk/_models/_workspace.py
argilla_sdk/_resource.py
argilla_sdk/client.py
argilla_sdk/datasets/__init__.py
argilla_sdk-0.1.0a3.dist-info/RECORD
