Metadata-Version: 2.1
Name: argilla-sdk
Version: 0.1.0a3
Summary: The Argilla python server SDK
Author-Email: Argilla <contact@argilla.io>
License: Apache 2.0
Requires-Python: <3.12,>=3.10
Requires-Dist: httpx>=0.26.0
Requires-Dist: pydantic<3.0.0,>=2.6.0
